gd_excelexporter/__init__.py
gd_excelexporter/__main__.py
gd_excelexporter/babel/__init__.py
gd_excelexporter/babel/csharp.py
gd_excelexporter/babel/godot.py
gd_excelexporter/babel/json.py
gd_excelexporter/cli.py
gd_excelexporter/config.py
gd_excelexporter/core/__init__.py
gd_excelexporter/core/engine.py
gd_excelexporter/core/generator.py
gd_excelexporter/core/models.py
gd_excelexporter/core/type_define.py
gd_excelexporter/engines/__init__.py
gd_excelexporter/engines/xlrd_engine.py
gd_excelexporter/engines/xlwings_engine.py
gd_excelexporter/exceptions.py
gd_excelexporter/generators/__init__.py
gd_excelexporter/generators/gds1/__init__.py
gd_excelexporter/generators/gds1/data_template.gd
gd_excelexporter/generators/gds1/setting_template.gd
gd_excelexporter/generators/gds2/__init__.py
gd_excelexporter/generators/gds2/data_template.gd
gd_excelexporter/generators/gds2/setting_template.gd
gd_excelexporter/generators/json1/__init__.py
gd_excelexporter/generators/json2/__init__.py
gd_excelexporter/generators/resource/__init__.py
gd_excelexporter/logger.py
gd_excelexporter/template/babel.cfg
gd_excelexporter/template/gen_all.bat
gd_excelexporter/template/gen_pot.bat
gd_excelexporter/template/reg/删除右键导出.reg
gd_excelexporter/template/reg/删除右键导出所有.reg
gd_excelexporter/template/reg/添加右键导出.reg
gd_excelexporter/template/reg/添加右键导出所有.reg
gd_excelexporter/template/sample/示例.xlsx
gd_excelexporter/type_defines/__init__.py
gd_excelexporter/type_defines/array.py
gd_excelexporter/type_defines/array_bool.py
gd_excelexporter/type_defines/array_str.py
gd_excelexporter/type_defines/bool.py
gd_excelexporter/type_defines/dict.py
gd_excelexporter/type_defines/float.py
gd_excelexporter/type_defines/function.py
gd_excelexporter/type_defines/int.py
gd_excelexporter/type_defines/string.py
gd_excelexporter/type_defines/tr_array_str.py
gd_excelexporter/type_defines/tr_dict.py
gd_excelexporter/type_defines/tr_string.py
gd_excelexporter-3.0.1.dist-info/LICENSE
gd_excelexporter-3.0.1.dist-info/METADATA
gd_excelexporter-3.0.1.dist-info/WHEEL
gd_excelexporter-3.0.1.dist-info/entry_points.txt
gd_excelexporter-3.0.1.dist-info/RECORD
