Metadata-Version: 2.1
Name: gd_excelexporter
Version: 3.0.1
Summary: Godot Excel导表工具
License: MIT
Author: kaluluosi
Author-email: kaluluosi@gamil.com
Requires-Python: >=3.8
Classifier: License :: OSI Approved :: MIT License
Classifier: Programming Language :: Python :: 3
Classifier: Programming Language :: Python :: 3.8
Classifier: Programming Language :: Python :: 3.9
Classifier: Programming Language :: Python :: 3.10
Classifier: Programming Language :: Python :: 3.11
Classifier: Programming Language :: Python :: 3.12
Requires-Dist: babel (>=2.12.1,<3.0.0)
Requires-Dist: click (>=8.1.3,<9.0.0)
Requires-Dist: importlib-metadata (>=6.1.0,<7.0.0) ; python_version == "38"
Requires-Dist: jinja2 (>=3.1.2,<4.0.0)
Requires-Dist: pydantic (>=2.7.0,<3.0.0)
Requires-Dist: setuptools (>=67.6.1,<68.0.0)
Requires-Dist: toml (>=0.10.2,<0.11.0)
Requires-Dist: xlrd (==1.2)
Requires-Dist: xlwings (>=0.31.1,<0.32.0)
